{"stats":{"minecraft:killed":{"minecraft:sheep":1,"minecraft:chicken":2},"minecraft:custom":{"minecraft:time_since_rest":21472,"minecraft:sprint_one_cm":62343,"minecraft:damage_taken":70,"minecraft:walk_one_cm":57266,"minecraft:mob_kills":25,"minecraft:drop":33,"minecraft:damage_dealt":1311,"minecraft:swim_one_cm":554,"minecraft:fly_one_cm":148662,"minecraft:crouch_one_cm":1612,"minecraft:play_time":22930,"minecraft:deaths":1,"minecraft:sneak_time":351,"minecraft:walk_under_water_one_cm":349,"minecraft:jump":720,"minecraft:leave_game":4,"minecraft:time_since_death":21458,"minecraft:walk_on_water_one_cm":2980,"minecraft:total_world_time":45535,"minecraft:climb_one_cm":4499,"minecraft:fall_one_cm":10856},"minecraft:dropped":{"birb:water_element":7,"minecraft:porkchop":11,"minecraft:wheat_seeds":5,"birb:earth_element":6,"birb:wind_element":5,"birb:fire_element":5,"minecraft:chicken":1,"minecraft:feather":1,"minecraft:leather":1,"minecraft:egg":1},"minecraft:mined":{"minecraft:fire":1,"minecraft:grass":16,"minecraft:tall_grass":1,"minecraft:fern":4},"minecraft:used":{"minecraft:grass_block":1,"minecraft:chicken":2,"minecraft:pig_spawn_egg":10,"minecraft:egg":8,"minecraft:cooked_beef":2},"minecraft:picked_up":{"minecraft:cooked_beef":3,"minecraft:feather":1,"minecraft:chicken":3,"minecraft:leather":1,"birb:water_element":7,"birb:earth_element":6,"minecraft:porkchop":11,"birb:fire_element":5,"birb:wind_element":5,"minecraft:wheat_seeds":5,"minecraft:egg":1}},"DataVersion":3120}